{
  "_fv": 57,
  "_type": "structure",
  "definition": {
    "structure": "enderman_castle_light",
    "projection": "terrain_matching",
    "ignoredBlocks": [
      {
        "value": "Blocks.STRUCTURE_BLOCK"
      }
    ],
    "spacing": 64,
    "separation": 16,
    "restrictionBiomes": [
      {
        "value": "end_barrens"
      },
      {
        "value": "end_midlands"
      },
      {
        "value": "small_end_islands"
      },
      {
        "value": "end_highlands"
      }
    ],
    "surfaceDetectionType": "MOTION_BLOCKING",
    "terrainAdaptation": "beard_thin",
    "generationStep": "SURFACE_STRUCTURES"
  }
}